flask_kafka/__init__.py
flask_kafka/consumer.py
flask_kafka/consumer_legacy.py
flask_kafka/flask_kafka.py
flask_kafka/producer.py
flask_kafka-0.1.0.dist-info/METADATA
flask_kafka-0.1.0.dist-info/WHEEL
flask_kafka-0.1.0.dist-info/top_level.txt
flask_kafka-0.1.0.dist-info/RECORD
