Metadata-Version: 2.1
Name: flask-kafka
Version: 0.1.0
Summary: An easy to use kafka consumer that uses the confluent kafka library, it runs concurrently with your flask server
Home-page: https://github.com/nimzymaina/flask_kafka
Author: Nimrod Kevin Maina
Author-email: nimzy.maina@gmail.com
License: MIT
Keywords: kafka,consumer,kafkaesque,flask,simple,consumer,flask style,decorator
Requires-Dist: kafka-python
Requires-Dist: confluent-kafka
